jsrocket-0.1.0.dist-info/licenses/LICENSE
rocket/__init__.py
rocket/logger/__init__.py
rocket/logger/config/dev.yaml
rocket/logger/config/prod.yaml
rocket/logger/config/test.yaml
rocket/logger/core/__init__.py
rocket/logger/core/formatter.py
rocket/logger/core/logger.py
rocket/logger/utils/__init__.py
rocket/logger/utils/config_loader.py
rocket/logger/utils/config_models.py
jsrocket-0.1.0.dist-info/METADATA
jsrocket-0.1.0.dist-info/WHEEL
jsrocket-0.1.0.dist-info/top_level.txt
jsrocket-0.1.0.dist-info/RECORD
