Metadata-Version: 2.4
Name: jsrocket
Version: 0.1.0
Summary: Production-ready Python logging library with built-in configurations for dev/test/prod environments
Author-email: JohnsonSmile <johnsonsmile@163.com>
License: MIT
Project-URL: Homepage, https://github.com/johnsonsmile/rocket
Project-URL: Documentation, https://github.com/johnsonsmile/rocket#readme
Project-URL: Repository, https://github.com/johnsonsmile/rocket
Project-URL: Issues, https://github.com/johnsonsmile/rocket/issues
Keywords: logging,logger,production,configuration,yaml
Classifier: Development Status :: 4 - Beta
Classifier: Intended Audience :: Developers
Classifier: License :: OSI Approved :: MIT License
Classifier: Programming Language :: Python :: 3
Classifier: Programming Language :: Python :: 3.13
Classifier: Topic :: Software Development :: Libraries :: Python Modules
Classifier: Topic :: System :: Logging
Requires-Python: >=3.13
License-File: LICENSE
Requires-Dist: pyyaml>=6.0.0
Requires-Dist: pydantic>=2.0.0
Dynamic: license-file
